{"nodes": [{"id": "c_users_win11_desktop_learnsrinagar_learnsrinagar_in_src_components_ui_tabs_jsx", "label": "tabs.jsx", "file_type": "code", "source_file": "C:\\Users\\WIN11\\Desktop\\LearnSrinagar\\learnsrinagar.in\\src\\components\\ui\\tabs.jsx", "source_location": "L1"}, {"id": "tabs_tabs", "label": "Tabs()", "file_type": "code", "source_file": "C:\\Users\\WIN11\\Desktop\\LearnSrinagar\\learnsrinagar.in\\src\\components\\ui\\tabs.jsx", "source_location": "L6"}, {"id": "tabs_tabslist", "label": "TabsList()", "file_type": "code", "source_file": "C:\\Users\\WIN11\\Desktop\\LearnSrinagar\\learnsrinagar.in\\src\\components\\ui\\tabs.jsx", "source_location": "L18"}, {"id": "tabs_tabstrigger", "label": "TabsTrigger()", "file_type": "code", "source_file": "C:\\Users\\WIN11\\Desktop\\LearnSrinagar\\learnsrinagar.in\\src\\components\\ui\\tabs.jsx", "source_location": "L33"}, {"id": "tabs_tabscontent", "label": "TabsContent()", "file_type": "code", "source_file": "C:\\Users\\WIN11\\Desktop\\LearnSrinagar\\learnsrinagar.in\\src\\components\\ui\\tabs.jsx", "source_location": "L48"}], "edges": [{"source": "c_users_win11_desktop_learnsrinagar_learnsrinagar_in_src_components_ui_tabs_jsx", "target": "react", "relation": "imports_from", "confidence": "EXTRACTED", "source_file": "C:\\Users\\WIN11\\Desktop\\LearnSrinagar\\learnsrinagar.in\\src\\components\\ui\\tabs.jsx", "source_location": "L1", "weight": 1.0}, {"source": "c_users_win11_desktop_learnsrinagar_learnsrinagar_in_src_components_ui_tabs_jsx", "target": "react_tabs", "relation": "imports_from", "confidence": "EXTRACTED", "source_file": "C:\\Users\\WIN11\\Desktop\\LearnSrinagar\\learnsrinagar.in\\src\\components\\ui\\tabs.jsx", "source_location": "L2", "weight": 1.0}, {"source": "c_users_win11_desktop_learnsrinagar_learnsrinagar_in_src_components_ui_tabs_jsx", "target": "utils", "relation": "imports_from", "confidence": "EXTRACTED", "source_file": "C:\\Users\\WIN11\\Desktop\\LearnSrinagar\\learnsrinagar.in\\src\\components\\ui\\tabs.jsx", "source_location": "L4", "weight": 1.0}, {"source": "c_users_win11_desktop_learnsrinagar_learnsrinagar_in_src_components_ui_tabs_jsx", "target": "tabs_tabs", "relation": "contains", "confidence": "EXTRACTED", "source_file": "C:\\Users\\WIN11\\Desktop\\LearnSrinagar\\learnsrinagar.in\\src\\components\\ui\\tabs.jsx", "source_location": "L6", "weight": 1.0}, {"source": "c_users_win11_desktop_learnsrinagar_learnsrinagar_in_src_components_ui_tabs_jsx", "target": "tabs_tabslist", "relation": "contains", "confidence": "EXTRACTED", "source_file": "C:\\Users\\WIN11\\Desktop\\LearnSrinagar\\learnsrinagar.in\\src\\components\\ui\\tabs.jsx", "source_location": "L18", "weight": 1.0}, {"source": "c_users_win11_desktop_learnsrinagar_learnsrinagar_in_src_components_ui_tabs_jsx", "target": "tabs_tabstrigger", "relation": "contains", "confidence": "EXTRACTED", "source_file": "C:\\Users\\WIN11\\Desktop\\LearnSrinagar\\learnsrinagar.in\\src\\components\\ui\\tabs.jsx", "source_location": "L33", "weight": 1.0}, {"source": "c_users_win11_desktop_learnsrinagar_learnsrinagar_in_src_components_ui_tabs_jsx", "target": "tabs_tabscontent", "relation": "contains", "confidence": "EXTRACTED", "source_file": "C:\\Users\\WIN11\\Desktop\\LearnSrinagar\\learnsrinagar.in\\src\\components\\ui\\tabs.jsx", "source_location": "L48", "weight": 1.0}], "raw_calls": [{"caller_nid": "tabs_tabs", "callee": "cn", "source_file": "C:\\Users\\WIN11\\Desktop\\LearnSrinagar\\learnsrinagar.in\\src\\components\\ui\\tabs.jsx", "source_location": "L13"}, {"caller_nid": "tabs_tabslist", "callee": "cn", "source_file": "C:\\Users\\WIN11\\Desktop\\LearnSrinagar\\learnsrinagar.in\\src\\components\\ui\\tabs.jsx", "source_location": "L25"}, {"caller_nid": "tabs_tabstrigger", "callee": "cn", "source_file": "C:\\Users\\WIN11\\Desktop\\LearnSrinagar\\learnsrinagar.in\\src\\components\\ui\\tabs.jsx", "source_location": "L40"}, {"caller_nid": "tabs_tabscontent", "callee": "cn", "source_file": "C:\\Users\\WIN11\\Desktop\\LearnSrinagar\\learnsrinagar.in\\src\\components\\ui\\tabs.jsx", "source_location": "L55"}]}